memory_trail/__init__.py
memory_trail/cli.py
memory_trail-0.0.1.dist-info/METADATA
memory_trail-0.0.1.dist-info/WHEEL
memory_trail-0.0.1.dist-info/entry_points.txt
memory_trail-0.0.1.dist-info/RECORD
